{
  "db_name": "SQLite",
  "query": "\n        SELECT\n            id,\n            user_id,\n            filename,\n            uuid_filename\n        FROM image_model\n        WHERE user_id = $1 ORDER BY id DESC LIMIT $2\n        ",
  "describe": {
    "columns": [
      {
        "name": "id",
        "ordinal": 0,
        "type_info": "Text"
      },
      {
        "name": "user_id",
        "ordinal": 1,
        "type_info": "Text"
      },
      {
        "name": "filename",
        "ordinal": 2,
        "type_info": "Text"
      },
      {
        "name": "uuid_filename",
        "ordinal": 3,
        "type_info": "Text"
      }
    ],
    "parameters": {
      "Right": 2
    },
    "nullable": [
      false,
      false,
      false,
      false
    ]
  },
  "hash": "277160da7fab46aa984e10e21e3a2927650e116b46305c704d26400022519ecf"
}
